py_trace/__init__.py
py_trace/_version.py
py_trace/client.py
py_trace/exceptions.py
py_trace-0.1.1.dist-info/DESCRIPTION.rst
py_trace-0.1.1.dist-info/METADATA
py_trace-0.1.1.dist-info/RECORD
py_trace-0.1.1.dist-info/WHEEL
py_trace-0.1.1.dist-info/metadata.json
py_trace-0.1.1.dist-info/top_level.txt
