Metadata-Version: 2.0
Name: py-trace
Version: 0.1.1
Summary: Python client for interacting with the Trace api.
Home-page: https://github.com/aiguofer/py-trace
Author: Diego Fernandez
Author-email: aiguo.fernandez@gmail.com
License: MIT license
Keywords: py_trace
Platform: UNKNOWN
Classifier: Development Status :: 2 - Pre-Alpha
Classifier: Intended Audience :: Developers
Classifier: License :: OSI Approved :: MIT License
Classifier: Natural Language :: English
Classifier: Programming Language :: Python :: 2
Classifier: Programming Language :: Python :: 2.7
Classifier: Programming Language :: Python :: 3
Classifier: Programming Language :: Python :: 3.4
Classifier: Programming Language :: Python :: 3.5
Classifier: Programming Language :: Python :: 3.6
Requires-Dist: requests-oauthlib
Provides-Extra: dev
Requires-Dist: pip (==9.0.1); extra == 'dev'
Requires-Dist: bumpversion (==0.5.3); extra == 'dev'
Requires-Dist: wheel (==0.30.0); extra == 'dev'
Requires-Dist: watchdog (==0.8.3); extra == 'dev'
Requires-Dist: flake8 (==3.5.0); extra == 'dev'
Requires-Dist: tox (==2.9.1); extra == 'dev'
Requires-Dist: coverage (==4.5.1); extra == 'dev'
Requires-Dist: Sphinx (==1.7.1); extra == 'dev'
Requires-Dist: twine (==1.10.0); extra == 'dev'
Requires-Dist: pytest (==3.4.2); extra == 'dev'
Requires-Dist: pytest-runner (==2.11.1); extra == 'dev'
